accesibilidad_web/__init__.py
accesibilidad_web/accesibilidad.py
accesibilidad_web/motor_imagen.py
accesibilidad_web/motor_voz.py
accesibilidad_web-0.1.0.dist-info/METADATA
accesibilidad_web-0.1.0.dist-info/WHEEL
accesibilidad_web-0.1.0.dist-info/top_level.txt
accesibilidad_web-0.1.0.dist-info/RECORD
