Metadata-Version: 2.4
Name: accesibilidad-web
Version: 0.1.0
Summary: Librería de accesibilidad web con reconocimiento de voz y gestos
Author: AKITSUAKANE
License: MIT
Requires-Python: >=3.8
Requires-Dist: SpeechRecognition
Requires-Dist: PyAudio
Requires-Dist: opencv-python
Requires-Dist: numpy
